speech_analysis_module/__init__.py
speech_analysis_module/speech_analysis_module.py
speech_analysis_module/analysis/__init__.py
speech_analysis_module/analysis/analysis.py
speech_analysis_module/features/__init__.py
speech_analysis_module/features/features.py
speech_analysis_module/plot/__init__.py
speech_analysis_module/plot/plot.py
speech_analysis_module/prepro/__init__.py
speech_analysis_module/prepro/prepro.py
speech_analysis_module/psychopy/__init__.py
speech_analysis_module/psychopy/recorder.py
speech_analysis_module/samples/01.wav
speech_analysis_module/samples/02.wav
speech_analysis_module/samples/03.wav
speech_analysis_module/samples/04.wav
speech_analysis_module/samples/05.wav
speech_analysis_module/utils/__init__.py
speech_analysis_module/utils/utils.py
speech_analysis_module-0.0.3.dist-info/licenses/license.txt
speech_analysis_module-0.0.3.dist-info/METADATA
speech_analysis_module-0.0.3.dist-info/WHEEL
speech_analysis_module-0.0.3.dist-info/top_level.txt
speech_analysis_module-0.0.3.dist-info/RECORD
