Metadata-Version: 2.4
Name: speech-analysis-module
Version: 0.0.3
Summary: SAM is a Python library for sound/audio processing in experimental psychology
Author-email: Emma Rico Martín <emmaricomartin@gmail.com>
License-Expression: GPL-3.0-only
Project-URL: Homepage, https://github.com/emmaricomartin/Speech-Analysis-Module
Classifier: Programming Language :: Python :: 3
Classifier: Operating System :: OS Independent
Requires-Python: >=3.10
License-File: license.txt
Requires-Dist: librosa
Requires-Dist: numpy
Requires-Dist: scipy
Requires-Dist: matplotlib
Requires-Dist: soundfile
Requires-Dist: sounddevice
Requires-Dist: pydub
Requires-Dist: praat-parselmouth
Requires-Dist: whisper
Requires-Dist: imageio-ffmpeg
Requires-Dist: serial
Dynamic: license-file
